dash_dropdown_components/Dropdown.py
dash_dropdown_components/MultiLevelDropdown.py
dash_dropdown_components/__init__.py
dash_dropdown_components/_imports_.py
dash_dropdown_components/dash_dropdown_components.min.js
dash_dropdown_components/dash_dropdown_components.min.js.map
dash_dropdown_components/metadata.json
dash_dropdown_components/package-info.json
dash_dropdown_components-0.0.15.dist-info/LICENSE
dash_dropdown_components-0.0.15.dist-info/METADATA
dash_dropdown_components-0.0.15.dist-info/WHEEL
dash_dropdown_components-0.0.15.dist-info/top_level.txt
dash_dropdown_components-0.0.15.dist-info/RECORD
