Metadata-Version: 2.1
Name: dash-dropdown-components
Version: 0.0.15
Summary: Dropdown components for Dash
Author: Wouter Wakker <wouter.wakker@outlook.com>
License: MIT
Classifier: Framework :: Dash
License-File: LICENSE
